llama_index/readers/paddle_ocr/__init__.py
llama_index/readers/paddle_ocr/base.py
llama_index_readers_paddle_ocr-0.1.0.dist-info/METADATA
llama_index_readers_paddle_ocr-0.1.0.dist-info/WHEEL
llama_index_readers_paddle_ocr-0.1.0.dist-info/licenses/LICENSE
llama_index_readers_paddle_ocr-0.1.0.dist-info/RECORD
