Metadata-Version: 2.4
Name: llama-index-readers-paddle-ocr
Version: 0.1.0
Summary: llama-index readers paddle_ocr integration
Author-email: Michael M L Ye <1156961988@qq.com>
Maintainer: mdarshad1000
License-Expression: MIT
License-File: LICENSE
Keywords: academic papers,ocr,pdf
Requires-Python: <4.0,>=3.9
Requires-Dist: llama-index-core<0.15,>=0.13.0
Requires-Dist: paddleocr>=2.7.0
Requires-Dist: paddlepaddle==3.2.0
Requires-Dist: pdfplumber==0.11.7
Requires-Dist: pillow==10.4.0
Requires-Dist: pymupdf==1.26.4
Requires-Dist: requests>=2.0.0
